[
  {
    "question": "逃げ馬が2頭以上存在する場合の展開予想として最も適切な判断は？",
    "choice1": "ハイペースになり後方の馬に有利な展開となる",
    "choice2": "マイペースで逃げられるため逃げ馬有利となる",
    "choice3": "ペースが遅くなりやすく差し馬有利となる",
    "choice4": "先行馬がレースをコントロールする展開となる",
    "correctIndex": 1,
    "explanation": "複数の逃げ馬が存在すると先頭争いが激しくなり、叩き合いによってハイペースになります。その結果、前の馬がバテて差し馬や追込馬といった後方の馬に有利な展開となることが記事で説明されています。",
    "difficulty": 5
  },
  {
    "question": "スローペース予想時の馬券戦略として最も理にかなっているのは？",
    "choice1": "追込一発狙いの高配当馬券を中心に購入する",
    "choice2": "差し馬の単勝・馬連を積極的に狙う",
    "choice3": "逃げ・先行馬と能力上位馬を中心とした馬券構成にする",
    "choice4": "展開が読めないので幅広い脚質をカバーする",
    "correctIndex": 3,
    "explanation": "スローペースでは体力を温存できる逃げ・先行馬が有利になり、最後は瞬発力勝負となるため能力上位馬も狙い目です。記事では追込一発狙いの高配当はスローペース時に避けるべき馬券として挙げられています。",
    "difficulty": 5
  },
  {
    "question": "展開予想における「複数シナリオ」の考え方として最も適切なのは？",
    "choice1": "メインシナリオを決めたら対抗シナリオは考えない方が集中できる",
    "choice2": "基本パターンと条件分岐を想定し2-3通りの可能性に対応する",
    "choice3": "可能性をすべて網羅するため5パターン以上用意する必要がある",
    "choice4": "展開予想は当てるものなので最も確率の高い1パターンに絞る",
    "correctIndex": 2,
    "explanation": "記事では展開予想を「当てる」ものではなく「可能性を絞り込む」ツールとし、2-3パターンのシナリオを用意することを推奨しています。条件分岐を考慮したメインシナリオと対抗シナリオの設定が重要です。",
    "difficulty": 5
  },
  {
    "question": "ミドルペース展開で最も有利とされる脚質の組み合わせは？",
    "choice1": "逃げ・追込",
    "choice2": "先行・差し",
    "choice3": "逃げ・先行",
    "choice4": "差し・追込",
    "correctIndex": 2,
    "explanation": "記事のペース別有利脚質の表によると、ミドルペースでは先行・差し馬がバランス良く力を発揮できるとされています。極端に前や後ろではなく、中間的な脚質が最も適したペース設定です。",
    "difficulty": 5
  },
  {
    "question": "先行馬の展開への影響として最も重要な役割は？",
    "choice1": "常に逃げ馬を追いかけて叩き合いを演出する",
    "choice2": "後方から一気に上がってきて勝負を決める",
    "choice3": "レースの流れをコントロールし展開の要となる",
    "choice4": "スタートから先頭に立ってマイペースを作る",
    "correctIndex": 3,
    "explanation": "記事では先行馬について「展開の要となることが多く、レースの流れをコントロールする重要な存在」と説明されています。逃げ馬がいない場合は自ら先頭に立つこともある柔軟性も持っています。",
    "difficulty": 5
  },
  {
    "question": "「逃げ馬独走型」展開パターンの条件と結果として正しいのは？",
    "choice1": "逃げ馬が2頭以上でハイペースになり差し馬有利",
    "choice2": "逃げ馬が1頭でマイペース進行し押し切りやすい",
    "choice3": "逃げ馬が0頭でスローペースとなり能力勝負",
    "choice4": "先行馬が複数で激突しバテて後続に有利",
    "correctIndex": 2,
    "explanation": "記事の展開パターン例で「逃げ馬独走型」は逃げ馬が1頭だけの場合に発生し、マイペースで楽に先頭を進めるため、後続が追いつけずそのまま押し切るケースが多いと説明されています。",
    "difficulty": 5
  },
  {
    "question": "展開予想でペースを左右する最も重要な要因は？",
    "choice1": "コース形状と直線の長さ",
    "choice2": "馬場状態の良不良",
    "choice3": "距離設定の長短",
    "choice4": "逃げ馬・先行馬の数と能力",
    "correctIndex": 4,
    "explanation": "記事では複数の要因を挙げた上で「特に重要なのは先頭争いの激しさ」と明記し、複数の逃げ馬や積極的な先行馬がいるとハイペースになる可能性が高まると説明されています。",
    "difficulty": 5
  },
  {
    "question": "リスクヘッジを考慮した馬券戦略の具体例として適切なのは？",
    "choice1": "確実性を重視してメインシナリオの馬のみに全額投資",
    "choice2": "基本はA馬中心だがスローならB馬も危険なのでB馬も少し押さえる",
    "choice3": "展開が読めない時は馬券購入を見送る",
    "choice4": "高配当を狙って対抗シナリオの馬により多く投資",
    "correctIndex": 2,
    "explanation": "記事では具体例として「基本はハイペースでA馬有利だが、スローになればB馬も危険」という場合、A馬中心にしつつB馬も少し押さえる戦略が効果的と説明されており、これがリスク分散の考え方です。",
    "difficulty": 5
  },
  {
    "question": "展開予想の習得において最も重要な取り組み方は？",
    "choice1": "理論を完璧に覚えてから実践に移る",
    "choice2": "的中率を最優先に一つのパターンを極める",
    "choice3": "レース映像の確認と予想・実際の比較を継続する",
    "choice4": "短期間で成果を出すため集中的に勉強する",
    "correctIndex": 3,
    "explanation": "記事のまとめで「展開予想は一朝一夕で身につくものではない」とし、レース映像を見返したり自分の予想と実際の展開を比較したりして継続的にスキルアップを図ることの重要性が強調されています。",
    "difficulty": 5
  },
  {
    "question": "差し・追込馬が最も苦戦しやすい展開条件は？",
    "choice1": "複数の逃げ馬によるハイペース展開",
    "choice2": "先行馬同士の激しい競り合い",
    "choice3": "積極的に行く馬がいない極端なスローペース",
    "choice4": "逃げ馬1頭によるミドルペース展開",
    "correctIndex": 3,
    "explanation": "記事では差し・追込馬について「前が速いペースになるほど有利になりますが、極端なスローペースでは届かないリスクがある」と説明されており、スローペース時は体力を温存した前の馬が最後まで粘れるためです。",
    "difficulty": 5
  }
]