[
  {
    "question": "ドウデュースが制覇した2つのG1レースの組み合わせはどれですか？",
    "choice1": "日本ダービーとジャパンカップ",
    "choice2": "日本ダービーと天皇賞（春）",
    "choice3": "ジャパンカップと有馬記念",
    "choice4": "天皇賞（春）と有馬記念",
    "correctIndex": 1,
    "explanation": "ドウデュースは2022年の日本ダービーと2023年のジャパンカップで1着となり、G1を2勝しています。天皇賞（春）は2着、有馬記念は3着でした。この2つのG1勝利が種牡馬としての評価ポイントの一つとなっています。",
    "difficulty": 1
  },
  {
    "question": "ドウデュースの父馬はどの馬ですか？",
    "choice1": "サンデーサイレンス",
    "choice2": "ディープインパクト",
    "choice3": "ハーツクライ",
    "choice4": "ダンスインザダーク",
    "correctIndex": 3,
    "explanation": "ドウデュースの父はハーツクライです。ハーツクライ系は日本の競馬界で非常に成功を収めている系統で、芝コースでの高い適性や中距離から長距離への対応力などの特徴があります。ダンスインザダークは母系の血統です。",
    "difficulty": 1
  },
  {
    "question": "ジャパンカップでドウデュースが勝利した距離は何メートルですか？",
    "choice1": "芝2000m",
    "choice2": "芝2400m",
    "choice3": "芝2500m",
    "choice4": "芝3200m",
    "correctIndex": 2,
    "explanation": "ドウデュースは芝2400mのジャパンカップで勝利を収めました。この勝利により距離適性の幅広さを証明しており、この特徴は種牡馬としても重要な要素とされています。日本ダービーとは異なる距離での勝利が評価されています。",
    "difficulty": 1
  },
  {
    "question": "ハーツクライ系の産駒として記事で挙げられているG1馬はどれですか？",
    "choice1": "オルフェーヴルとゴールドシップ",
    "choice2": "シャフリヤールとヴェルトライゼンデ",
    "choice3": "ドゥラメンテとキタサンブラック",
    "choice4": "コントレイルとグランアレグリア",
    "correctIndex": 2,
    "explanation": "記事では、ハーツクライ産駒の代表例として「シャフリヤールやヴェルトライゼンデ」など数多くのG1馬が挙げられています。この系統の安定した成績は種牡馬選びの重要な指標となると説明されています。",
    "difficulty": 1
  },
  {
    "question": "ドウデュースの競走スタイルの特徴として記述されているのはどれですか？",
    "choice1": "逃げと瞬発力",
    "choice2": "先行力と粘り強さ",
    "choice3": "差しと爆発力",
    "choice4": "追込みと持続力",
    "correctIndex": 2,
    "explanation": "ドウデュースの競走スタイルは「先行力と粘り強さ」を兼ね備えた理想的なものと記述されています。レースでは常に好位につけ、直線での伸び脚が特徴的で、この競走センスの高さは産駒にも受け継がれることが期待されています。",
    "difficulty": 1
  },
  {
    "question": "ハーツクライ系の特徴として記事に記載されていないのはどれですか？",
    "choice1": "芝コースでの高い適性",
    "choice2": "中距離から長距離への対応力",
    "choice3": "ダートコースでの高い適性",
    "choice4": "気性の良さと競走意欲の高さ",
    "correctIndex": 3,
    "explanation": "記事では、ハーツクライ系の特徴として「芝コースでの高い適性」「中距離から長距離への対応力」「気性の良さと競走意欲の高さ」「成長力の豊富さ」が挙げられています。ダートコースでの適性については言及されていません。",
    "difficulty": 1
  },
  {
    "question": "ドウデュースが日本ダービーで勝利したのは何年ですか？",
    "choice1": "2021年",
    "choice2": "2022年",
    "choice3": "2023年",
    "choice4": "2024年",
    "correctIndex": 2,
    "explanation": "ドウデュースは2022年の日本ダービーで勝利しています。この勝利により3歳世代の頂点に君臨しました。翌2023年にはジャパンカップでも勝利を収め、G1を2勝する実績を残しました。",
    "difficulty": 1
  },
  {
    "question": "記事によると、ドウデュースの母系にはどの馬の血が流れていますか？",
    "choice1": "サンデーサイレンス",
    "choice2": "ノーザンテースト",
    "choice3": "ダンスインザダーク",
    "choice4": "トニービン",
    "correctIndex": 3,
    "explanation": "ドウデュースの母系にはダンスインザダークの血が流れています。このスピードとスタミナを兼ね備えた血統構成が、ドウデュースの競走能力の高さに繋がり、種牡馬としても様々な牝馬との配合で面白い産駒が期待できるとされています。",
    "difficulty": 1
  },
  {
    "question": "種牡馬としてのドウデュースの評価ポイントに含まれないのはどれですか？",
    "choice1": "G1を2勝した実績",
    "choice2": "ハーツクライ系の優秀な血統背景",
    "choice3": "ダートG1での勝利経験",
    "choice4": "バランスの取れた体型と競走スタイル",
    "correctIndex": 3,
    "explanation": "記事では、種牡馬としての評価ポイントとして「G1を2勝した実績」「ハーツクライ系の優秀な血統背景」「バランスの取れた体型と競走スタイル」「気性面での優秀さ」が挙げられています。ダートG1での勝利については言及されていません。",
    "difficulty": 1
  },
  {
    "question": "記事で挙げられている配合相手として期待される母父系統に含まれないのはどれですか？",
    "choice1": "サンデーサイレンス系",
    "choice2": "ノーザンダンサー系",
    "choice3": "ミスタープロスペクター系",
    "choice4": "ハーツクライ系",
    "correctIndex": 4,
    "explanation": "記事では理想的な配合パターンとして、母父系統に「サンデーサイレンス系」「ノーザンダンサー系」「ミスタープロスペクター系」が挙げられています。ハーツクライ系はドウデュース自身の父系であり、配合相手の母父系統としては挙げられていません。",
    "difficulty": 1
  }
]